{"hourly": {"icon": "cloudy", "data": [{"ozone": 246.3, "windGust": 3.87, "temperature": 58.41, "icon": "rain", "precipType": "rain", "humidity": 0.75, "cloudCover": 0.71, "summary": "Drizzle", "apparentTemperature": 58.41, "pressure": 1023.8, "windSpeed": 3.27, "visibility": 9.207, "time": 1572303600, "windBearing": 151, "precipIntensity": 0.0005, "uvIndex": 0, "dewPoint": 50.53, "precipProbability": 0.97}, {"ozone": 246.5, "windGust": 7.33, "temperature": 57.09, "icon": "partly-cloudy-night", "precipType": "rain", "humidity": 0.79, "cloudCover": 0.62, "summary": "Mostly Cloudy", "apparentTemperature": 57.09, "pressure": 1024.47, "windSpeed": 3.67, "visibility": 8.938, "time": 1572307200, "windBearing": 134, "precipIntensity": 0.0002, "uvIndex": 0, "dewPoint": 50.53, "precipProbability": 0.09}, {"ozone": 246.4, "windGust": 12.36, "temperature": 56.47, "icon": "partly-cloudy-night", "dewPoint": 51.29, "humidity": 0.83, "cloudCover": 0.39, "summary": "Partly Cloudy", "apparentTemperature": 56.47, "pressure": 1024.88, "windSpeed": 5.47, "visibility": 10, "time": 1572310800, "windBearing": 115, "precipIntensity": 0, "uvIndex": 0, "precipProbability": 0}, {"ozone": 245.9, "windGust": 14.83, "temperature": 55.89, "icon": "partly-cloudy-night", "precipType": "rain", "humidity": 0.86, "cloudCover": 0.27, "summary": "Partly Cloudy", "apparentTemperature": 55.89, "pressure": 1025.39, "windSpeed": 6.19, "visibility": 10, "time": 1572314400, "windBearing": 107, "precipIntensity": 0.0015, "uvIndex": 0, "dewPoint": 51.84, "precipProbability": 0.02}, {"ozone": 245.3, "windGust": 15.03, "temperature": 55.51, "icon": "partly-cloudy-night", "precipType": "rain", "humidity": 0.87, "cloudCover": 0.34, "summary": "Partly Cloudy", "apparentTemperature": 55.51, "pressure": 1025.46, "windSpeed": 6.05, "visibility": 10, "time": 1572318000, "windBearing": 99, "precipIntensity": 0.0003, "uvIndex": 0, "dewPoint": 51.85, "precipProbability": 0.02}, {"ozone": 244.4, "windGust": 14.24, "temperature": 55.4, "icon": "partly-cloudy-night", "precipType": "rain", "humidity": 0.88, "cloudCover": 0.47, "summary": "Partly Cloudy", "apparentTemperature": 55.4, "pressure": 1025.94, "windSpeed": 6.06, "visibility": 10, "time": 1572321600, "windBearing": 88, "precipIntensity": 0.0025, "uvIndex": 0, "dewPoint": 51.86, "precipProbability": 0.02}, {"ozone": 243.2, "windGust": 12.75, "temperature": 55.64, "icon": "partly-cloudy-night", "precipType": "rain", "humidity": 0.88, "cloudCover": 0.64, "summary": "Mostly Cloudy", "apparentTemperature": 55.64, "pressure": 1025.86, "windSpeed": 6.23, "visibility": 10, "time": 1572325200, "windBearing": 83, "precipIntensity": 0.0012, "uvIndex": 0, "dewPoint": 52.14, "precipProbability": 0.02}, {"ozone": 242.6, "windGust": 11.79, "temperature": 56.21, "icon": "partly-cloudy-night", "precipType": "rain", "humidity": 0.88, "cloudCover": 0.77, "summary": "Mostly Cloudy", "apparentTemperature": 56.21, "pressure": 1026.17, "windSpeed": 6.27, "visibility": 10, "time": 1572328800, "windBearing": 78, "precipIntensity": 0.0034, "uvIndex": 0, "dewPoint": 52.71, "precipProbability": 0.04}, {"ozone": 242.8, "windGust": 12.76, "temperature": 56.66, "icon": "cloudy", "precipType": "rain", "humidity": 0.88, "cloudCover": 0.88, "summary": "Overcast", "apparentTemperature": 56.66, "pressure": 1025.94, "windSpeed": 6.19, "visibility": 10, "time": 1572332400, "windBearing": 71, "precipIntensity": 0.003, "uvIndex": 0, "dewPoint": 53.15, "precipProbability": 0.04}, {"ozone": 243.6, "windGust": 13.72, "temperature": 57.09, "icon": "cloudy", "precipType": "rain", "humidity": 0.87, "cloudCover": 0.94, "summary": "Overcast", "apparentTemperature": 57.09, "pressure": 1025.74, "windSpeed": 6.6, "visibility": 10, "time": 1572336000, "windBearing": 79, "precipIntensity": 0.003, "uvIndex": 0, "dewPoint": 53.21, "precipProbability": 0.04}, {"ozone": 243.8, "windGust": 13.95, "temperature": 57.33, "icon": "cloudy", "precipType": "rain", "humidity": 0.86, "cloudCover": 0.95, "summary": "Overcast", "apparentTemperature": 57.33, "pressure": 1025.46, "windSpeed": 6.94, "visibility": 10, "time": 1572339600, "windBearing": 81, "precipIntensity": 0.0014, "uvIndex": 0, "dewPoint": 53.04, "precipProbability": 0.03}, {"ozone": 243.1, "windGust": 14.2, "temperature": 57.3, "icon": "cloudy", "precipType": "rain", "humidity": 0.85, "cloudCover": 0.92, "summary": "Overcast", "apparentTemperature": 57.3, "pressure": 1025.33, "windSpeed": 6.81, "visibility": 10, "time": 1572343200, "windBearing": 79, "precipIntensity": 0.001, "uvIndex": 0, "dewPoint": 52.88, "precipProbability": 0.02}, {"ozone": 242.2, "windGust": 14.87, "temperature": 57.38, "icon": "cloudy", "precipType": "rain", "humidity": 0.85, "cloudCover": 0.93, "summary": "Overcast", "apparentTemperature": 57.38, "pressure": 1025.48, "windSpeed": 6.78, "visibility": 10, "time": 1572346800, "windBearing": 83, "precipIntensity": 0.0008, "uvIndex": 0, "dewPoint": 52.86, "precipProbability": 0.02}, {"ozone": 241.6, "windGust": 15.02, "temperature": 57.62, "icon": "cloudy", "precipType": "rain", "humidity": 0.85, "cloudCover": 0.98, "summary": "Overcast", "apparentTemperature": 57.62, "pressure": 1025.98, "windSpeed": 6.79, "visibility": 10, "time": 1572350400, "windBearing": 83, "precipIntensity": 0.0014, "uvIndex": 0, "dewPoint": 53, "precipProbability": 0.03}, {"ozone": 241.8, "windGust": 14.67, "temperature": 58.22, "icon": "cloudy", "precipType": "rain", "humidity": 0.83, "cloudCover": 1, "summary": "Overcast", "apparentTemperature": 58.22, "pressure": 1026.12, "windSpeed": 7.11, "visibility": 10, "time": 1572354000, "windBearing": 83, "precipIntensity": 0.002, "uvIndex": 1, "dewPoint": 53.24, "precipProbability": 0.04}, {"ozone": 242.3, "windGust": 13.91, "temperature": 58.9, "icon": "cloudy", "precipType": "rain", "humidity": 0.83, "cloudCover": 1, "summary": "Overcast", "apparentTemperature": 58.9, "pressure": 1026.57, "windSpeed": 6.94, "visibility": 10, "time": 1572357600, "windBearing": 80, "precipIntensity": 0.0036, "uvIndex": 2, "dewPoint": 53.68, "precipProbability": 0.08}, {"ozone": 242.9, "windGust": 13.25, "temperature": 59.44, "icon": "cloudy", "precipType": "rain", "humidity": 0.83, "cloudCover": 1, "summary": "Overcast", "apparentTemperature": 59.44, "pressure": 1026.72, "windSpeed": 6.75, "visibility": 10, "time": 1572361200, "windBearing": 78, "precipIntensity": 0.0051, "uvIndex": 2, "dewPoint": 54.3, "precipProbability": 0.11}, {"ozone": 243.3, "windGust": 12.94, "temperature": 59.71, "icon": "cloudy", "precipType": "rain", "humidity": 0.83, "cloudCover": 1, "summary": "Overcast", "apparentTemperature": 59.71, "pressure": 1026.47, "windSpeed": 6.54, "visibility": 10, "time": 1572364800, "windBearing": 73, "precipIntensity": 0.0061, "uvIndex": 3, "dewPoint": 54.68, "precipProbability": 0.13}, {"ozone": 243.7, "windGust": 12.78, "temperature": 59.65, "icon": "cloudy", "precipType": "rain", "humidity": 0.83, "cloudCover": 0.99, "summary": "Overcast", "apparentTemperature": 59.65, "pressure": 1025.94, "windSpeed": 6.32, "visibility": 10, "time": 1572368400, "windBearing": 70, "precipIntensity": 0.0073, "uvIndex": 3, "dewPoint": 54.54, "precipProbability": 0.15}, {"ozone": 244.3, "windGust": 12.56, "temperature": 59.75, "icon": "cloudy", "precipType": "rain", "humidity": 0.83, "cloudCover": 0.99, "summary": "Overcast", "apparentTemperature": 59.75, "pressure": 1025.47, "windSpeed": 6.09, "visibility": 10, "time": 1572372000, "windBearing": 67, "precipIntensity": 0.008, "uvIndex": 3, "dewPoint": 54.5, "precipProbability": 0.16}, {"ozone": 244.9, "windGust": 12.12, "temperature": 59.82, "icon": "cloudy", "precipType": "rain", "humidity": 0.84, "cloudCover": 0.99, "summary": "Overcast", "apparentTemperature": 59.82, "pressure": 1025.15, "windSpeed": 5.88, "visibility": 10, "time": 1572375600, "windBearing": 66, "precipIntensity": 0.0069, "uvIndex": 2, "dewPoint": 54.83, "precipProbability": 0.13}, {"ozone": 245.8, "windGust": 11.55, "temperature": 59.9, "icon": "cloudy", "precipType": "rain", "humidity": 0.85, "cloudCover": 1, "summary": "Overcast", "apparentTemperature": 59.9, "pressure": 1024.92, "windSpeed": 5.63, "visibility": 10, "time": 1572379200, "windBearing": 66, "precipIntensity": 0.0055, "uvIndex": 1, "dewPoint": 55.27, "precipProbability": 0.1}, {"ozone": 246.3, "windGust": 10.97, "temperature": 60.29, "icon": "cloudy", "precipType": "rain", "humidity": 0.85, "cloudCover": 1, "summary": "Overcast", "apparentTemperature": 60.29, "pressure": 1024.82, "windSpeed": 5.37, "visibility": 10, "time": 1572382800, "windBearing": 64, "precipIntensity": 0.0051, "uvIndex": 0, "dewPoint": 55.7, "precipProbability": 0.09}, {"ozone": 246.4, "windGust": 10.49, "temperature": 60.64, "icon": "cloudy", "precipType": "rain", "humidity": 0.85, "cloudCover": 1, "summary": "Overcast", "apparentTemperature": 60.64, "pressure": 1025.06, "windSpeed": 5.15, "visibility": 10, "time": 1572386400, "windBearing": 61, "precipIntensity": 0.0048, "uvIndex": 0, "dewPoint": 56.17, "precipProbability": 0.07}, {"ozone": 246.4, "windGust": 10.02, "temperature": 60.57, "icon": "cloudy", "precipType": "rain", "humidity": 0.87, "cloudCover": 1, "summary": "Overcast", "apparentTemperature": 60.57, "pressure": 1025.43, "windSpeed": 4.93, "visibility": 10, "time": 1572390000, "windBearing": 59, "precipIntensity": 0.0048, "uvIndex": 0, "dewPoint": 56.71, "precipProbability": 0.07}, {"ozone": 246.4, "windGust": 9.35, "temperature": 60.63, "icon": "cloudy", "precipType": "rain", "humidity": 0.89, "cloudCover": 1, "summary": "Overcast", "apparentTemperature": 60.63, "pressure": 1025.71, "windSpeed": 4.71, "visibility": 10, "time": 1572393600, "windBearing": 57, "precipIntensity": 0.0052, "uvIndex": 0, "dewPoint": 57.24, "precipProbability": 0.06}, {"ozone": 246.1, "windGust": 8.24, "temperature": 60.72, "icon": "cloudy", "precipType": "rain", "humidity": 0.89, "cloudCover": 1, "summary": "Overcast", "apparentTemperature": 60.72, "pressure": 1025.75, "windSpeed": 4.38, "visibility": 10, "time": 1572397200, "windBearing": 61, "precipIntensity": 0.0049, "uvIndex": 0, "dewPoint": 57.48, "precipProbability": 0.06}, {"ozone": 245.9, "windGust": 6.92, "temperature": 60.8, "icon": "cloudy", "precipType": "rain", "humidity": 0.89, "cloudCover": 1, "summary": "Overcast", "apparentTemperature": 60.8, "pressure": 1025.66, "windSpeed": 4.01, "visibility": 10, "time": 1572400800, "windBearing": 66, "precipIntensity": 0.0048, "uvIndex": 0, "dewPoint": 57.63, "precipProbability": 0.05}, {"ozone": 245.8, "windGust": 5.86, "temperature": 60.91, "icon": "cloudy", "precipType": "rain", "humidity": 0.89, "cloudCover": 0.99, "summary": "Overcast", "apparentTemperature": 60.91, "pressure": 1025.56, "windSpeed": 3.8, "visibility": 10, "time": 1572404400, "windBearing": 67, "precipIntensity": 0.0051, "uvIndex": 0, "dewPoint": 57.75, "precipProbability": 0.06}, {"ozone": 245.8, "windGust": 5.26, "temperature": 61.13, "icon": "cloudy", "precipType": "rain", "humidity": 0.89, "cloudCover": 0.99, "summary": "Overcast", "apparentTemperature": 61.13, "pressure": 1025.46, "windSpeed": 3.8, "visibility": 10, "time": 1572408000, "windBearing": 58, "precipIntensity": 0.0067, "uvIndex": 0, "dewPoint": 57.77, "precipProbability": 0.07}, {"ozone": 246.1, "windGust": 4.98, "temperature": 61.29, "icon": "cloudy", "precipType": "rain", "humidity": 0.88, "cloudCover": 0.99, "summary": "Overcast", "apparentTemperature": 61.29, "pressure": 1025.37, "windSpeed": 3.94, "visibility": 10, "time": 1572411600, "windBearing": 45, "precipIntensity": 0.01, "uvIndex": 0, "dewPoint": 57.83, "precipProbability": 0.08}, {"ozone": 246.2, "windGust": 5.14, "temperature": 61.39, "icon": "cloudy", "precipType": "rain", "humidity": 0.89, "cloudCover": 0.99, "summary": "Overcast", "apparentTemperature": 61.39, "pressure": 1025.32, "windSpeed": 4.18, "visibility": 10, "time": 1572415200, "windBearing": 35, "precipIntensity": 0.0124, "uvIndex": 0, "dewPoint": 57.97, "precipProbability": 0.1}, {"ozone": 246.2, "windGust": 5.94, "temperature": 61.41, "icon": "cloudy", "precipType": "rain", "humidity": 0.89, "cloudCover": 0.99, "summary": "Overcast", "apparentTemperature": 61.42, "pressure": 1025.32, "windSpeed": 4.58, "visibility": 10, "time": 1572418800, "windBearing": 35, "precipIntensity": 0.0107, "uvIndex": 0, "dewPoint": 58.05, "precipProbability": 0.11}, {"ozone": 246.2, "windGust": 7.19, "temperature": 61.38, "icon": "cloudy", "precipType": "rain", "humidity": 0.89, "cloudCover": 1, "summary": "Overcast", "apparentTemperature": 61.38, "pressure": 1025.41, "windSpeed": 5.07, "visibility": 10, "time": 1572422400, "windBearing": 37, "precipIntensity": 0.0073, "uvIndex": 0, "dewPoint": 57.99, "precipProbability": 0.12}, {"ozone": 246.1, "windGust": 8.45, "temperature": 61.18, "icon": "cloudy", "precipType": "rain", "humidity": 0.89, "cloudCover": 1, "summary": "Overcast", "apparentTemperature": 61.18, "pressure": 1025.46, "windSpeed": 5.53, "visibility": 10, "time": 1572426000, "windBearing": 39, "precipIntensity": 0.0052, "uvIndex": 0, "dewPoint": 57.86, "precipProbability": 0.13}, {"ozone": 246, "windGust": 9.55, "temperature": 60.86, "icon": "cloudy", "precipType": "rain", "humidity": 0.89, "cloudCover": 1, "summary": "Overcast", "apparentTemperature": 60.86, "pressure": 1025.5, "windSpeed": 5.85, "visibility": 10, "time": 1572429600, "windBearing": 41, "precipIntensity": 0.0046, "uvIndex": 0, "dewPoint": 57.69, "precipProbability": 0.14}, {"ozone": 246, "windGust": 10.66, "temperature": 60.84, "icon": "cloudy", "precipType": "rain", "humidity": 0.89, "cloudCover": 1, "summary": "Overcast", "apparentTemperature": 60.84, "pressure": 1025.6, "windSpeed": 6.13, "visibility": 10, "time": 1572433200, "windBearing": 43, "precipIntensity": 0.0048, "uvIndex": 0, "dewPoint": 57.52, "precipProbability": 0.14}, {"ozone": 246.1, "windGust": 11.76, "temperature": 60.9, "icon": "cloudy", "precipType": "rain", "humidity": 0.88, "cloudCover": 0.99, "summary": "Overcast", "apparentTemperature": 60.9, "pressure": 1025.6, "windSpeed": 6.4, "visibility": 10, "time": 1572436800, "windBearing": 46, "precipIntensity": 0.0048, "uvIndex": 0, "dewPoint": 57.39, "precipProbability": 0.13}, {"ozone": 246.2, "windGust": 12.89, "temperature": 61.17, "icon": "cloudy", "precipType": "rain", "humidity": 0.87, "cloudCover": 0.99, "summary": "Overcast", "apparentTemperature": 61.17, "pressure": 1025.65, "windSpeed": 6.63, "visibility": 10, "time": 1572440400, "windBearing": 47, "precipIntensity": 0.0036, "uvIndex": 1, "dewPoint": 57.32, "precipProbability": 0.11}, {"ozone": 246.5, "windGust": 13.91, "temperature": 61.87, "icon": "cloudy", "precipType": "rain", "humidity": 0.86, "cloudCover": 0.99, "summary": "Overcast", "apparentTemperature": 61.87, "pressure": 1025.7, "windSpeed": 6.86, "visibility": 10, "time": 1572444000, "windBearing": 50, "precipIntensity": 0.0023, "uvIndex": 1, "dewPoint": 57.76, "precipProbability": 0.08}, {"ozone": 246.9, "windGust": 14.82, "temperature": 62.42, "icon": "cloudy", "precipType": "rain", "humidity": 0.86, "cloudCover": 1, "summary": "Overcast", "apparentTemperature": 62.42, "pressure": 1025.61, "windSpeed": 7.02, "visibility": 10, "time": 1572447600, "windBearing": 50, "precipIntensity": 0.0017, "uvIndex": 2, "dewPoint": 58.16, "precipProbability": 0.06}, {"ozone": 247.5, "windGust": 15.76, "temperature": 62.69, "icon": "cloudy", "precipType": "rain", "humidity": 0.85, "cloudCover": 1, "summary": "Overcast", "apparentTemperature": 62.69, "pressure": 1025.34, "windSpeed": 7.26, "visibility": 10, "time": 1572451200, "windBearing": 49, "precipIntensity": 0.0021, "uvIndex": 3, "dewPoint": 58.14, "precipProbability": 0.07}, {"ozone": 248, "windGust": 16.65, "temperature": 62.94, "icon": "cloudy", "precipType": "rain", "humidity": 0.83, "cloudCover": 1, "summary": "Overcast", "apparentTemperature": 62.94, "pressure": 1024.92, "windSpeed": 7.51, "visibility": 10, "time": 1572454800, "windBearing": 46, "precipIntensity": 0.0039, "uvIndex": 3, "dewPoint": 57.71, "precipProbability": 0.12}, {"ozone": 248.7, "windGust": 17.21, "temperature": 63.43, "icon": "cloudy", "precipType": "rain", "humidity": 0.81, "cloudCover": 1, "summary": "Overcast", "apparentTemperature": 63.43, "pressure": 1024.56, "windSpeed": 7.57, "visibility": 10, "time": 1572458400, "windBearing": 46, "precipIntensity": 0.0059, "uvIndex": 2, "dewPoint": 57.53, "precipProbability": 0.12}, {"ozone": 249.5, "windGust": 17.29, "temperature": 63.68, "icon": "cloudy", "precipType": "rain", "humidity": 0.82, "cloudCover": 1, "summary": "Overcast", "apparentTemperature": 63.68, "pressure": 1024.15, "windSpeed": 7.3, "visibility": 10, "time": 1572462000, "windBearing": 45, "precipIntensity": 0.0061, "uvIndex": 2, "dewPoint": 57.93, "precipProbability": 0.09}, {"ozone": 250.7, "windGust": 17, "temperature": 63.82, "icon": "cloudy", "precipType": "rain", "humidity": 0.83, "cloudCover": 1, "summary": "Overcast", "apparentTemperature": 63.82, "pressure": 1023.75, "windSpeed": 6.85, "visibility": 10, "time": 1572465600, "windBearing": 47, "precipIntensity": 0.0052, "uvIndex": 1, "dewPoint": 58.59, "precipProbability": 0.08}, {"ozone": 251.7, "windGust": 16.4, "temperature": 63.89, "icon": "cloudy", "precipType": "rain", "humidity": 0.85, "cloudCover": 1, "summary": "Overcast", "apparentTemperature": 63.96, "pressure": 1023.44, "windSpeed": 6.43, "visibility": 10, "time": 1572469200, "windBearing": 52, "precipIntensity": 0.0045, "uvIndex": 0, "dewPoint": 59.24, "precipProbability": 0.07}, {"ozone": 252.7, "windGust": 15.27, "temperature": 63.96, "icon": "cloudy", "precipType": "rain", "humidity": 0.86, "cloudCover": 1, "summary": "Overcast", "apparentTemperature": 64.1, "pressure": 1023.37, "windSpeed": 6.13, "visibility": 10, "time": 1572472800, "windBearing": 74, "precipIntensity": 0.0045, "uvIndex": 0, "dewPoint": 59.72, "precipProbability": 0.06}, {"ozone": 253.7, "windGust": 13.81, "temperature": 63.4, "icon": "cloudy", "precipType": "rain", "humidity": 0.88, "cloudCover": 1, "summary": "Overcast", "apparentTemperature": 63.56, "pressure": 1023.45, "windSpeed": 5.89, "visibility": 10, "time": 1572476400, "windBearing": 120, "precipIntensity": 0.0051, "uvIndex": 0, "dewPoint": 59.67, "precipProbability": 0.06}], "summary": "Overcast throughout the day."}, "alerts": [{"description": "...MINOR COASTAL FLOODING TONIGHT AND TUESDAY... ...COASTAL FLOOD ADVISORY REMAINS IN EFFECT FROM 8 AM TO NOON EDT TUESDAY... * LOCATIONS...In New Jersey, Hudson. In New York, New York (Manhattan) and Richmond (Staten Island). * TIMING...From 8 AM to noon EDT Tuesday. * COASTAL FLOOD IMPACTS...There is a low threat of property damage. Shallow flooding is expected in the most vulnerable locations near the waterfront and shoreline. Expect around 1 to 2 feet of inundation above ground level in low lying, vulnerable areas. Some roads and low lying properties including parking lots, parks, lawns, and homes and businesses with basements near the waterfront will experience shallow flooding. Time of high total tides are approximate to the nearest hour. NEW YORK HARBOR AT THE BATTERY NYC MLLW CATEGORIES - MINOR 7.2 FT, MODERATE 8.5 FT, MAJOR 9.6 FT MHHW CATEGORIES - MINOR 2.2 FT, MODERATE 3.5 FT, MAJOR 4.6 FT TOTAL TOTAL DEPARTURE DAY/TIME TIDE TIDE FROM NORM WAVES FLOOD FT MLLW FT MHHW FT FT IMPACT -------- --------- --------- --------- ------- -------- 28/09 PM 5.7/ 6.2 0.8/ 1.3 0.4/ 0.9 1 NONE 29/10 AM 7.1/ 7.6 2.1/ 2.6 1.0/ 1.5 1 MINOR 29/10 PM 5.4/ 5.9 0.4/ 0.9 0.2/ 0.7 1 NONE 30/10 AM 6.0/ 6.5 1.0/ 1.5 0.1/ 0.6 1 NONE KILL VAN KULL AT BERGEN POINT NY MLLW CATEGORIES - MINOR 7.2 FT, MODERATE 8.5 FT, MAJOR 9.6 FT MHHW CATEGORIES - MINOR 1.7 FT, MODERATE 3.0 FT, MAJOR 4.1 FT TOTAL TOTAL DEPARTURE DAY/TIME TIDE TIDE FROM NORM WAVES FLOOD FT MLLW FT MHHW FT FT IMPACT -------- --------- --------- --------- ------- -------- 28/09 PM 6.5/ 7.0 1.0/ 1.5 0.4/ 0.9 1 NONE 29/10 AM 7.7/ 8.2 2.2/ 2.7 1.0/ 1.5 1 MINOR 29/10 PM 5.9/ 6.4 0.4/ 0.9 0.1/ 0.6 1 NONE 30/10 AM 6.5/ 7.0 1.0/ 1.5 0.0/ 0.5 1 NONE &&\n", "title": "Coastal Flood Advisory", "expires": 1572364800, "uri": "https://alerts.weather.gov/cap/wwacapget.php?x=NY125D17102E54.CoastalFloodAdvisory.125D171EE840NY.OKXCFWOKX.4b68baecdef23cde134842794d76b38f", "regions": ["New York (Manhattan)", "Richmond (Staten Is.)"], "time": 1572350400, "severity": "advisory"}], "currently": {"ozone": 246.3, "windGust": 3.87, "temperature": 58.41, "dewPoint": 50.53, "precipType": "rain", "nearestStormDistance": 4, "precipIntensityError": 0, "humidity": 0.75, "nearestStormBearing": 323, "summary": "Drizzle", "apparentTemperature": 58.41, "pressure": 1023.8, "windSpeed": 3.27, "precipProbability": 0.97, "visibility": 9.207, "cloudCover": 0.71, "time": 1572303601, "windBearing": 151, "precipIntensity": 0.003, "uvIndex": 0, "icon": "rain"}, "longitude": -74.006, "flags": {"units": "us", "sources": ["nwspa", "cmc", "gfs", "hrrr", "icon", "isd", "madis", "nam", "sref", "darksky", "nearest-precip"], "nearest-station": 0.816}, "daily": {"icon": "rain", "data": [{"apparentTemperatureMinTime": 1572321600, "precipType": "rain", "temperatureLow": 54.75, "precipIntensityMaxTime": 1572321600, "temperatureMin": 54.75, "temperatureHigh": 63.41, "summary": "Mostly cloudy throughout the day.", "dewPoint": 50.31, "apparentTemperatureMax": 62.74, "temperatureMax": 63.41, "windSpeed": 4.23, "apparentTemperatureHigh": 62.74, "windGustTime": 1572318000, "temperatureMaxTime": 1572282000, "windBearing": 44, "temperatureLowTime": 1572321600, "moonPhase": 0.03, "temperatureMinTime": 1572321600, "windGust": 15.03, "apparentTemperatureLow": 55.4, "sunsetTime": 1572299948, "pressure": 1020.67, "uvIndexTime": 1572282000, "cloudCover": 0.58, "apparentTemperatureLowTime": 1572321600, "apparentTemperatureMin": 55.4, "apparentTemperatureHighTime": 1572282000, "precipIntensityMax": 0.0025, "icon": "partly-cloudy-day", "apparentTemperatureMaxTime": 1572282000, "humidity": 0.75, "ozone": 251.1, "temperatureHighTime": 1572282000, "visibility": 9.853, "time": 1572235200, "precipIntensity": 0.0002, "uvIndex": 4, "sunriseTime": 1572261770, "precipProbability": 0.06}, {"apparentTemperatureMinTime": 1572321600, "precipType": "rain", "temperatureLow": 59.92, "precipIntensityMaxTime": 1572372000, "temperatureMin": 54.75, "temperatureHigh": 61.31, "summary": "Overcast throughout the day.", "dewPoint": 54.65, "apparentTemperatureMax": 61.13, "temperatureMax": 61.8, "windSpeed": 5.84, "apparentTemperatureHigh": 60.64, "windGustTime": 1572350400, "temperatureMaxTime": 1572408000, "windBearing": 73, "temperatureLowTime": 1572390000, "moonPhase": 0.07, "temperatureMinTime": 1572321600, "windGust": 15.02, "apparentTemperatureLow": 60.57, "sunsetTime": 1572386271, "pressure": 1025.71, "uvIndexTime": 1572368400, "cloudCover": 0.94, "apparentTemperatureLowTime": 1572390000, "apparentTemperatureMin": 55.4, "apparentTemperatureHighTime": 1572386400, "precipIntensityMax": 0.008, "icon": "cloudy", "apparentTemperatureMaxTime": 1572408000, "humidity": 0.86, "ozone": 244.2, "temperatureHighTime": 1572386400, "visibility": 10, "time": 1572321600, "precipIntensity": 0.0041, "uvIndex": 3, "sunriseTime": 1572348240, "precipProbability": 0.33}, {"apparentTemperatureMinTime": 1572433200, "precipType": "rain", "temperatureLow": 60.81, "precipIntensityMaxTime": 1572415200, "temperatureMin": 60.19, "temperatureHigh": 64.63, "summary": "Overcast throughout the day.", "dewPoint": 58.45, "apparentTemperatureMax": 64.1, "temperatureMax": 64.63, "windSpeed": 5.98, "apparentTemperatureHigh": 64.1, "windGustTime": 1572462000, "temperatureMaxTime": 1572472800, "windBearing": 63, "temperatureLowTime": 1572516000, "moonPhase": 0.11, "temperatureMinTime": 1572433200, "windGust": 17.29, "apparentTemperatureLow": 61.5, "sunsetTime": 1572472595, "pressure": 1024.52, "uvIndexTime": 1572454800, "cloudCover": 0.99, "apparentTemperatureLowTime": 1572516000, "apparentTemperatureMin": 60.84, "apparentTemperatureHighTime": 1572472800, "precipIntensityMax": 0.0124, "icon": "rain", "apparentTemperatureMaxTime": 1572472800, "humidity": 0.87, "ozone": 249.6, "temperatureHighTime": 1572472800, "visibility": 9.945, "time": 1572408000, "precipIntensity": 0.005, "uvIndex": 3, "sunriseTime": 1572434710, "precipProbability": 0.39}, {"apparentTemperatureMinTime": 1572516000, "precipType": "rain", "temperatureLow": 57.43, "precipIntensityMaxTime": 1572577200, "temperatureMin": 60.81, "temperatureHigh": 69.83, "summary": "Light rain and dangerously windy throughout the day.", "dewPoint": 60.7, "apparentTemperatureMax": 69.44, "temperatureMax": 69.83, "windSpeed": 10.24, "apparentTemperatureHigh": 69.44, "windGustTime": 1572580800, "temperatureMaxTime": 1572559200, "windBearing": 189, "temperatureLowTime": 1572609600, "moonPhase": 0.14, "temperatureMinTime": 1572516000, "windGust": 42.5, "apparentTemperatureLow": 58.08, "sunsetTime": 1572558921, "pressure": 1015.8, "uvIndexTime": 1572541200, "cloudCover": 0.96, "apparentTemperatureLowTime": 1572609600, "apparentTemperatureMin": 61.5, "apparentTemperatureHighTime": 1572559200, "precipIntensityMax": 0.0825, "icon": "rain", "apparentTemperatureMaxTime": 1572559200, "humidity": 0.85, "ozone": 264.1, "temperatureHighTime": 1572559200, "visibility": 9.973, "time": 1572494400, "precipIntensity": 0.0221, "uvIndex": 3, "sunriseTime": 1572521181, "precipProbability": 0.98}, {"apparentTemperatureMinTime": 1572667200, "precipType": "rain", "temperatureLow": 42.48, "precipIntensityMaxTime": 1572598800, "temperatureMin": 46.6, "temperatureHigh": 62.24, "summary": "Light rain in the morning.", "dewPoint": 45.41, "apparentTemperatureMax": 69.35, "temperatureMax": 69.48, "windSpeed": 15.85, "apparentTemperatureHigh": 61.57, "windGustTime": 1572591600, "temperatureMaxTime": 1572595200, "windBearing": 260, "temperatureLowTime": 1572692400, "moonPhase": 0.17, "temperatureMinTime": 1572667200, "windGust": 48.39, "apparentTemperatureLow": 38.87, "sunsetTime": 1572645248, "pressure": 1015.09, "uvIndexTime": 1572627600, "cloudCover": 0.45, "apparentTemperatureLowTime": 1572692400, "apparentTemperatureMin": 43.22, "apparentTemperatureHighTime": 1572606000, "precipIntensityMax": 0.0773, "icon": "rain", "apparentTemperatureMaxTime": 1572595200, "humidity": 0.64, "ozone": 279.2, "temperatureHighTime": 1572606000, "visibility": 9.466, "time": 1572580800, "precipIntensity": 0.0178, "uvIndex": 3, "sunriseTime": 1572607651, "precipProbability": 0.98}, {"apparentTemperatureMinTime": 1572692400, "precipType": "rain", "temperatureLow": 43.52, "precipIntensityMaxTime": 1572717600, "temperatureMin": 42.48, "temperatureHigh": 58.27, "summary": "Clear throughout the day.", "dewPoint": 36.43, "apparentTemperatureMax": 57.6, "temperatureMax": 58.27, "windSpeed": 7.11, "apparentTemperatureHigh": 57.6, "windGustTime": 1572739200, "temperatureMaxTime": 1572721200, "windBearing": 309, "temperatureLowTime": 1572782400, "moonPhase": 0.21, "temperatureMinTime": 1572692400, "windGust": 17.04, "apparentTemperatureLow": 39.16, "sunsetTime": 1572731577, "pressure": 1020.66, "uvIndexTime": 1572714000, "cloudCover": 0, "apparentTemperatureLowTime": 1572782400, "apparentTemperatureMin": 38.87, "apparentTemperatureHighTime": 1572721200, "precipIntensityMax": 0.0046, "icon": "clear-day", "apparentTemperatureMaxTime": 1572721200, "humidity": 0.59, "ozone": 294.2, "temperatureHighTime": 1572721200, "visibility": 10, "time": 1572667200, "precipIntensity": 0.0005, "uvIndex": 3, "sunriseTime": 1572694122, "precipProbability": 0.06}, {"apparentTemperatureMinTime": 1572782400, "precipType": "rain", "temperatureLow": 37.57, "precipIntensityMaxTime": 1572760800, "temperatureMin": 43.3, "temperatureHigh": 54.39, "summary": "Clear throughout the day.", "dewPoint": 32.49, "apparentTemperatureMax": 53.72, "temperatureMax": 54.39, "windSpeed": 9.55, "apparentTemperatureHigh": 53.72, "windGustTime": 1572825600, "temperatureMaxTime": 1572807600, "windBearing": 299, "temperatureLowTime": 1572865200, "moonPhase": 0.24, "temperatureMinTime": 1572843600, "windGust": 20.39, "apparentTemperatureLow": 34.17, "sunsetTime": 1572817907, "pressure": 1019.88, "uvIndexTime": 1572800400, "cloudCover": 0.07, "apparentTemperatureLowTime": 1572865200, "apparentTemperatureMin": 39.16, "apparentTemperatureHighTime": 1572807600, "precipIntensityMax": 0.0003, "icon": "clear-day", "apparentTemperatureMaxTime": 1572807600, "humidity": 0.54, "ozone": 321.9, "temperatureHighTime": 1572807600, "visibility": 10, "time": 1572753600, "precipIntensity": 0.0001, "uvIndex": 3, "sunriseTime": 1572780593, "precipProbability": 0.08}, {"apparentTemperatureMinTime": 1572865200, "precipType": "rain", "temperatureLow": 49.02, "precipIntensityMaxTime": 1572901200, "temperatureMin": 37.57, "temperatureHigh": 55.95, "summary": "Partly cloudy throughout the day.", "dewPoint": 32.03, "apparentTemperatureMax": 55.28, "temperatureMax": 55.95, "windSpeed": 6.43, "apparentTemperatureHigh": 55.28, "windGustTime": 1572930000, "temperatureMaxTime": 1572897600, "windBearing": 224, "temperatureLowTime": 1572951600, "moonPhase": 0.27, "temperatureMinTime": 1572865200, "windGust": 17.51, "apparentTemperatureLow": 48.13, "sunsetTime": 1572904235, "pressure": 1026.98, "uvIndexTime": 1572883200, "cloudCover": 0.08, "apparentTemperatureLowTime": 1572951600, "apparentTemperatureMin": 34.17, "apparentTemperatureHighTime": 1572897600, "precipIntensityMax": 0.0004, "icon": "partly-cloudy-day", "apparentTemperatureMaxTime": 1572897600, "humidity": 0.55, "ozone": 311, "temperatureHighTime": 1572897600, "visibility": 10, "time": 1572843600, "precipIntensity": 0.0001, "uvIndex": 3, "sunriseTime": 1572867068, "precipProbability": 0.01}], "summary": "Light rain on Wednesday through Friday, with high temperatures peaking at 69\u00b0F on Thursday."}, "offset": -4, "latitude": 40.7128, "timezone": "America/New_York", "minutely": {"icon": "rain", "data": [{"precipIntensityError": 0, "precipIntensity": 0.003, "precipType": "rain", "precipProbability": 0.97, "time": 1572303600}, {"precipIntensityError": 0, "precipIntensity": 0.003, "precipType": "rain", "precipProbability": 0.95, "time": 1572303660}, {"precipIntensityError": 0, "precipIntensity": 0.003, "precipType": "rain", "precipProbability": 0.9, "time": 1572303720}, {"precipIntensityError": 0, "precipIntensity": 0.003, "precipType": "rain", "precipProbability": 0.82, "time": 1572303780}, {"precipIntensityError": 0, "precipIntensity": 0.003, "precipType": "rain", "precipProbability": 0.75, "time": 1572303840}, {"precipIntensityError": 0, "precipIntensity": 0.003, "precipType": "rain", "precipProbability": 0.66, "time": 1572303900}, {"precipIntensityError": 0.001, "precipIntensity": 0.003, "precipType": "rain", "precipProbability": 0.59, "time": 1572303960}, {"precipIntensityError": 0.001, "precipIntensity": 0.003, "precipType": "rain", "precipProbability": 0.53, "time": 1572304020}, {"precipIntensityError": 0.001, "precipIntensity": 0.003, "precipType": "rain", "precipProbability": 0.5, "time": 1572304080}, {"precipIntensity": 0, "precipProbability": 0, "time": 1572304140}, {"precipIntensity": 0, "precipProbability": 0, "time": 1572304200}, {"precipIntensity": 0, "precipProbability": 0, "time": 1572304260}, {"precipIntensity": 0, "precipProbability": 0, "time": 1572304320}, {"precipIntensity": 0, "precipProbability": 0, "time": 1572304380}, {"precipIntensity": 0, "precipProbability": 0, "time": 1572304440}, {"precipIntensity": 0, "precipProbability": 0, "time": 1572304500}, {"precipIntensity": 0, "precipProbability": 0, "time": 1572304560}, {"precipIntensity": 0, "precipProbability": 0, "time": 1572304620}, {"precipIntensity": 0, "precipProbability": 0, "time": 1572304680}, {"precipIntensity": 0, "precipProbability": 0, "time": 1572304740}, {"precipIntensity": 0, "precipProbability": 0, "time": 1572304800}, {"precipIntensity": 0, "precipProbability": 0, "time": 1572304860}, {"precipIntensity": 0, "precipProbability": 0, "time": 1572304920}, {"precipIntensity": 0, "precipProbability": 0, "time": 1572304980}, {"precipIntensity": 0, "precipProbability": 0, "time": 1572305040}, {"precipIntensity": 0, "precipProbability": 0, "time": 1572305100}, {"precipIntensity": 0, "precipProbability": 0, "time": 1572305160}, {"precipIntensity": 0, "precipProbability": 0, "time": 1572305220}, {"precipIntensity": 0, "precipProbability": 0, "time": 1572305280}, {"precipIntensity": 0, "precipProbability": 0, "time": 1572305340}, {"precipIntensity": 0, "precipProbability": 0, "time": 1572305400}, {"precipIntensity": 0, "precipProbability": 0, "time": 1572305460}, {"precipIntensity": 0, "precipProbability": 0, "time": 1572305520}, {"precipIntensity": 0, "precipProbability": 0, "time": 1572305580}, {"precipIntensity": 0, "precipProbability": 0, "time": 1572305640}, {"precipIntensity": 0, "precipProbability": 0, "time": 1572305700}, {"precipIntensity": 0, "precipProbability": 0, "time": 1572305760}, {"precipIntensity": 0, "precipProbability": 0, "time": 1572305820}, {"precipIntensity": 0, "precipProbability": 0, "time": 1572305880}, {"precipIntensity": 0, "precipProbability": 0, "time": 1572305940}, {"precipIntensity": 0, "precipProbability": 0, "time": 1572306000}, {"precipIntensity": 0, "precipProbability": 0, "time": 1572306060}, {"precipIntensity": 0, "precipProbability": 0, "time": 1572306120}, {"precipIntensity": 0, "precipProbability": 0, "time": 1572306180}, {"precipIntensity": 0, "precipProbability": 0, "time": 1572306240}, {"precipIntensity": 0, "precipProbability": 0, "time": 1572306300}, {"precipIntensity": 0, "precipProbability": 0, "time": 1572306360}, {"precipIntensity": 0, "precipProbability": 0, "time": 1572306420}, {"precipIntensity": 0, "precipProbability": 0, "time": 1572306480}, {"precipIntensity": 0, "precipProbability": 0, "time": 1572306540}, {"precipIntensity": 0, "precipProbability": 0, "time": 1572306600}, {"precipIntensity": 0, "precipProbability": 0, "time": 1572306660}, {"precipIntensity": 0, "precipProbability": 0, "time": 1572306720}, {"precipIntensity": 0, "precipProbability": 0, "time": 1572306780}, {"precipIntensity": 0, "precipProbability": 0, "time": 1572306840}, {"precipIntensity": 0, "precipProbability": 0, "time": 1572306900}, {"precipIntensity": 0, "precipProbability": 0, "time": 1572306960}, {"precipIntensityError": 0.001, "precipIntensity": 0.003, "precipType": "rain", "precipProbability": 0.09, "time": 1572307020}, {"precipIntensityError": 0.001, "precipIntensity": 0.003, "precipType": "rain", "precipProbability": 0.09, "time": 1572307080}, {"precipIntensityError": 0.001, "precipIntensity": 0.003, "precipType": "rain", "precipProbability": 0.08, "time": 1572307140}, {"precipIntensityError": 0.001, "precipIntensity": 0.003, "precipType": "rain", "precipProbability": 0.08, "time": 1572307200}], "summary": "Possible drizzle stopping in 9 min."}}